README.md
setup.py
AppTrack.egg-info/PKG-INFO
AppTrack.egg-info/SOURCES.txt
AppTrack.egg-info/dependency_links.txt
AppTrack.egg-info/entry_points.txt
AppTrack.egg-info/not-zip-safe
AppTrack.egg-info/requires.txt
AppTrack.egg-info/top_level.txt
apptrack/__init__.py
apptrack/codecs.py
apptrack/config.py
apptrack/constants.py
apptrack/db.py
apptrack/metrics.py
apptrack/reporter.py
apptrack/sampler.py
apptrack/span.py
apptrack/span_context.py
apptrack/thrift.py
apptrack/tracer.py
apptrack/utils.py
apptrack/backend/__init__.py
apptrack/backend/memory.py
apptrack/backend/mongo.py
apptrack/tracing/__init__.py
apptrack/tracing/trace.py
apptrack/web/__init__.py
apptrack/web/flask_ability.py